genomepy/__about__.py
genomepy/__init__.py
genomepy/argparse_support.py
genomepy/caching.py
genomepy/cli.py
genomepy/exceptions.py
genomepy/files.py
genomepy/functions.py
genomepy/online.py
genomepy/seq.py
genomepy/utils.py
genomepy/annotation/__init__.py
genomepy/annotation/mygene.py
genomepy/annotation/sanitize.py
genomepy/annotation/utils.py
genomepy/config/__init__.py
genomepy/config/default.yaml
genomepy/genome/__init__.py
genomepy/genome/sequences.py
genomepy/plugins/__init__.py
genomepy/plugins/blacklist.py
genomepy/plugins/bowtie2.py
genomepy/plugins/bwa.py
genomepy/plugins/gmap.py
genomepy/plugins/hisat2.py
genomepy/plugins/minimap2.py
genomepy/plugins/star.py
genomepy/providers/__init__.py
genomepy/providers/base.py
genomepy/providers/ensembl.py
genomepy/providers/gencode.py
genomepy/providers/local.py
genomepy/providers/ncbi.py
genomepy/providers/ucsc.py
genomepy/providers/url.py
genomepy-0.16.3.dist-info/METADATA
genomepy-0.16.3.dist-info/WHEEL
genomepy-0.16.3.dist-info/entry_points.txt
genomepy-0.16.3.dist-info/licenses/LICENSE
genomepy-0.16.3.dist-info/RECORD
