Metadata-Version: 2.4
Name: genomepy
Version: 0.16.3
Summary: Genes and genomes at your fingertips
Project-URL: Homepage, https://github.com/vanheeringen-lab/genomepy
Project-URL: Documentation, https://vanheeringen-lab.github.io/genomepy/
Project-URL: News, https://github.com/vanheeringen-lab/genomepy/blob/master/CHANGELOG.md
Project-URL: Readme, https://github.com/vanheeringen-lab/genomepy/blob/master/README.md
Author-email: Siebren Frölich <siebrenf@gmail.com>, Maarten van der Sande <m.vandersande@science.ru.nl>, Tilman Schäfers <tilman.schaefers@ru.nl>, Simon van Heeringen <simon.vanheeringen@gmail.com>
Maintainer-email: Siebren Frölich <siebrenf@gmail.com>, Simon van Heeringen <simon.vanheeringen@gmail.com>
License: MIT License
License-File: LICENSE
Keywords: Ensembl,GENCODE,NCBI,UCSC,annotation,assembly,gene,genome
Classifier: Development Status :: 4 - Beta
Classifier: Intended Audience :: Developers
Classifier: Intended Audience :: Science/Research
Classifier: License :: OSI Approved :: MIT License
Classifier: Operating System :: MacOS :: MacOS X
Classifier: Operating System :: POSIX :: Linux
Classifier: Programming Language :: Python
Classifier: Programming Language :: Python :: 3
Classifier: Topic :: Scientific/Engineering :: Bio-Informatics
Requires-Python: >=3.9
Requires-Dist: appdirs
Requires-Dist: biopython>=1.73
Requires-Dist: click
Requires-Dist: colorama
Requires-Dist: diskcache
Requires-Dist: filelock>=3.5
Requires-Dist: loguru
Requires-Dist: mygene
Requires-Dist: mysql-connector-python<=8.4
Requires-Dist: numpy
Requires-Dist: pandas
Requires-Dist: pyfaidx>=0.7.2.1
Requires-Dist: pyyaml
Requires-Dist: requests
Requires-Dist: tqdm>=4.51
